strapi.py
strapi-0.0.1.dist-info/LICENSE
strapi-0.0.1.dist-info/METADATA
strapi-0.0.1.dist-info/WHEEL
strapi-0.0.1.dist-info/top_level.txt
strapi-0.0.1.dist-info/RECORD
