Metadata-Version: 2.1
Name: strapi
Version: 0.0.1
Summary: Strapt SDK for Python.
Home-page: https://github.com/princeshaji/strapi-sdk-python
Author: Prince Shaji
Author-email: 22243569+PrinceShaji@users.noreply.github.com
License: UNKNOWN
Platform: UNKNOWN
Classifier: Programming Language :: Python :: 3
Classifier: Programming Language :: Python :: 3.6
Classifier: Programming Language :: Python :: 3.7
Classifier: License :: OSI Approved :: MIT License
Classifier: Operating System :: OS Independent
